LICENSE
p115oss/__init__.py
p115oss/py.typed
p115oss-0.0.8.dist-info/LICENSE
p115oss-0.0.8.dist-info/LICENSE_zh
p115oss-0.0.8.dist-info/METADATA
p115oss-0.0.8.dist-info/WHEEL
p115oss-0.0.8.dist-info/RECORD
